nendo_plugin_library_postgres/__init__.py
nendo_plugin_library_postgres/config.py
nendo_plugin_library_postgres/model.py
nendo_plugin_library_postgres/plugin.py
nendo_plugin_library_postgres/storage.py
nendo_plugin_library_postgres-0.1.5.dist-info/LICENSE
nendo_plugin_library_postgres-0.1.5.dist-info/METADATA
nendo_plugin_library_postgres-0.1.5.dist-info/WHEEL
nendo_plugin_library_postgres-0.1.5.dist-info/RECORD
