Metadata-Version: 2.1
Name: nendo_plugin_library_postgres
Version: 0.1.5
Summary: PostgresDB implementation of the Nendo Library plugin. Comes with support for track embeddings.
Home-page: https://okio.ai
License: MIT
Keywords: nendo,AI,Machine Learning,Audio,Generative,Library,Plugin
Author: Okio Team
Author-email: team@okio.ai
Requires-Python: >=3.8,<3.11
Classifier: Development Status :: 5 - Production/Stable
Classifier: Environment :: Console
Classifier: Intended Audience :: Developers
Classifier: License :: OSI Approved :: MIT License
Classifier: Operating System :: OS Independent
Classifier: Programming Language :: Python :: 3
Classifier: Programming Language :: Python :: 3.8
Classifier: Programming Language :: Python :: 3.9
Classifier: Programming Language :: Python :: 3.10
Requires-Dist: asyncpg (>=0.28.0,<0.29.0)
Requires-Dist: google-cloud-storage (>=2.12.0,<3.0.0)
Requires-Dist: nendo (>=0.2.0,<0.3.0)
Requires-Dist: numpy (>=1.20,<2.0)
Requires-Dist: pgvector (>=0.2.4,<0.3.0)
Requires-Dist: psycopg2 (>=2.9.9,<3.0.0)
Requires-Dist: pydantic (>=2.0.0,<2.5.0)
Requires-Dist: sqlalchemy (>=2.0.25,<3.0.0)
Requires-Dist: sqlalchemy-json (>=0.7.0,<0.8.0)
Project-URL: Repository, https://github.com/okio-ai/nendo_plugin_library_postgres
